anal_chem/__init__.py
anal_chem/estimator.py
anal_chem/outlier_filter.py
anal_chem/statistics.py
anal_chem-0.0.0.dist-info/LICENSE
anal_chem-0.0.0.dist-info/METADATA
anal_chem-0.0.0.dist-info/WHEEL
anal_chem-0.0.0.dist-info/top_level.txt
anal_chem-0.0.0.dist-info/RECORD
