Metadata-Version: 2.1
Name: anal-chem
Version: 0.0.0
Summary: 分析化学中常用函数实现
Home-page: https://github.com/Enzyme125/anal_chem
Author: Y.C. Long
Author-email: 847072154@qq.com
License: MIT
Keywords: chemistry,analytical chemistry
Platform: UNKNOWN
Classifier: Development Status :: 2 - Pre-Alpha
Classifier: Intended Audience :: Developers
Classifier: License :: OSI Approved :: MIT License
Classifier: Natural Language :: Chinese (Simplified)
Classifier: Natural Language :: English
Classifier: Operating System :: MacOS
Classifier: Operating System :: Microsoft :: Windows
Classifier: Operating System :: POSIX :: Linux
Classifier: Programming Language :: Python :: 3
Classifier: Programming Language :: Python :: 3.5
Classifier: Programming Language :: Python :: 3.6
Classifier: Programming Language :: Python :: 3.7
Classifier: Programming Language :: Python :: 3.8
Classifier: Programming Language :: Python :: 3 :: Only
Classifier: Topic :: Utilities
Requires-Python: >=3.8, <4
License-File: LICENSE
Requires-Dist: setuptools (>=58.0.4)
Requires-Dist: numpy (>=1.20.3)
Requires-Dist: scipy (>=1.7.1)
